setup.py
bldsunnyday.egg-info/PKG-INFO
bldsunnyday.egg-info/SOURCES.txt
bldsunnyday.egg-info/dependency_links.txt
bldsunnyday.egg-info/requires.txt
bldsunnyday.egg-info/top_level.txt
sunnyday/__init__.py
sunnyday/sunnyday.py